{
  "title": "SSI SET - Lorient",
  "children": [
    {
      "id": "l1",
      "title": "L1",
      "children": [
        {
          "id": "l1cupge",
          "title": "L1 CUPGE",
          "children": [
            {
              "id": "l1cupge13temps",
              "title": "L1 CUPGE 1/3 temps",
              "url": "https://planning.univ-ubs.fr/jsp/custom/modules/plannings/anonymous_cal.jsp?resources=9396&projectId=1&calType=ical&firstDate={date-start}&lastDate={date-end}"
            },
            {
              "id": "l1cupgesemestre1",
              "title": "Semestre 1",
              "children": [
                {
                  "id": "cupge_11amth1106-phy1112-chi1104-phy1113-mth1107-mph1102",
                  "title": "CUPGE_1 / 1a",
                  "url": "https://planning.univ-ubs.fr/jsp/custom/modules/plannings/anonymous_cal.jsp?resources=795&projectId=1&calType=ical&firstDate={date-start}&lastDate={date-end}"
                },
                {
                  "id": "cupge_11bmth1106-phy1112-inf1109-phy1113-mth1107-mph1102",
                  "title": "CUPGE_1 / 1b",
                  "url": "https://planning.univ-ubs.fr/jsp/custom/modules/plannings/anonymous_cal.jsp?resources=5381&projectId=1&calType=ical&firstDate={date-start}&lastDate={date-end}"
                }
              ]
            },
            {
              "id": "l1cupgesemestre2",
              "title": "Semestre 2",
              "children": [
                {
                  "id": "cupge_11amth1206-phy1212-chi1207-mth1207-phy1213-mph1202",
                  "title": "CUPGE_1 / 1a",
                  "url": "https://planning.univ-ubs.fr/jsp/custom/modules/plannings/anonymous_cal.jsp?resources=6548&projectId=1&calType=ical&firstDate={date-start}&lastDate={date-end}"
                },
                {
                  "id": "cupge_11bmth1206-phy1212-inf1210-mth1207-phy1213-mph1202",
                  "title": "CUPGE_1 / 1b",
                  "url": "https://planning.univ-ubs.fr/jsp/custom/modules/plannings/anonymous_cal.jsp?resources=8071&projectId=1&calType=ical&firstDate={date-start}&lastDate={date-end}"
                }
              ]
            }
          ]
        },
        {
          "id": "l1eemte",
          "title": "L1 EE / MTE",
          "children": [
            {
              "id": "l1eemte13temps",
              "title": "L1 EE / MTE 1/3 temps",
              "url": "https://planning.univ-ubs.fr/jsp/custom/modules/plannings/anonymous_cal.jsp?resources=9395&projectId=1&calType=ical&firstDate={date-start}&lastDate={date-end}"
            },
            {
              "id": "l1eemtesemestre1",
              "title": "Semestre 1",
              "children": [
                {
                  "id": "ee_13mth1106-phy1112-etd1101-phy1113-sdi1101",
                  "title": "EE_1 / 3",
                  "url": "https://planning.univ-ubs.fr/jsp/custom/modules/plannings/anonymous_cal.jsp?resources=3830&projectId=1&calType=ical&firstDate={date-start}&lastDate={date-end}"
                },
                {
                  "id": "mte_14mth1106-sdi1102-chi1104-etd1101-sdi1101",
                  "title": "MTE_1 / 4",
                  "url": "https://planning.univ-ubs.fr/jsp/custom/modules/plannings/anonymous_cal.jsp?resources=4016&projectId=1&calType=ical&firstDate={date-start}&lastDate={date-end}"
                }
              ]
            },
            {
              "id": "l1eemtesemestre2",
              "title": "Semestre 2",
              "children": [
                {
                  "id": "ee_13mth1206-phy1212-een1201-mtx1201-ers1201",
                  "title": "EE_1 / 3",
                  "url": "https://planning.univ-ubs.fr/jsp/custom/modules/plannings/anonymous_cal.jsp?resources=5617&projectId=1&calType=ical&firstDate={date-start}&lastDate={date-end}"
                },
                {
                  "id": "mte_14mth1206-sdi1201-een1201-mtx1201-ers1201",
                  "title": "MTE_1 / 4",
                  "url": "https://planning.univ-ubs.fr/jsp/custom/modules/plannings/anonymous_cal.jsp?resources=7205&projectId=1&calType=ical&firstDate={date-start}&lastDate={date-end}"
                }
              ]
            }
          ]
        },
        {
          "id": "l1meca-gc",
          "title": "L1 Méca-GC",
          "children": [
            {
              "id": "l1meca-gc13temps",
              "title": "L1 Méca-GC 1/3 temps",
              "url": "https://planning.univ-ubs.fr/jsp/custom/modules/plannings/anonymous_cal.jsp?resources=9394&projectId=1&calType=ical&firstDate={date-start}&lastDate={date-end}"
            },
            {
              "id": "l1meca-gcsemestre1",
              "title": "Semestre 1",
              "children": [
                {
                  "id": "meca-gc_15amth1106-sdi1102-chi1104-phy1113-sdi1101",
                  "title": "Méca-GC_1 / 5a",
                  "children": [
                    {
                      "id": "meca-gc_15a1mth1106-sdi1102-chi1104-phy1113-sdi1101",
                      "title": "Méca-GC_1 / 5a1",
                      "url": "https://planning.univ-ubs.fr/jsp/custom/modules/plannings/anonymous_cal.jsp?resources=7250&projectId=1&calType=ical&firstDate={date-start}&lastDate={date-end}"
                    },
                    {
                      "id": "meca-gc_15a2mth1106-sdi1102-chi1104-phy1113-sdi1101",
                      "title": "Méca-GC_1 / 5a2",
                      "url": "https://planning.univ-ubs.fr/jsp/custom/modules/plannings/anonymous_cal.jsp?resources=6913&projectId=1&calType=ical&firstDate={date-start}&lastDate={date-end}"
                    }
                  ]
                },
                {
                  "id": "meca-gc_15bmth1106-sdi1102-inf1109-phy1113-sdi1101",
                  "title": "Méca-GC_1 / 5b",
                  "children": [
                    {
                      "id": "meca-gc_15b1mth1106-sdi1102-inf1109-phy1113-sdi1101",
                      "title": "Méca-GC_1 / 5b1",
                      "url": "https://planning.univ-ubs.fr/jsp/custom/modules/plannings/anonymous_cal.jsp?resources=7259&projectId=1&calType=ical&firstDate={date-start}&lastDate={date-end}"
                    },
                    {
                      "id": "meca-gc_15b2mth1106-sdi1102-inf1109-phy1113-sdi1101",
                      "title": "Méca-GC_1 / 5b2",
                      "url": "https://planning.univ-ubs.fr/jsp/custom/modules/plannings/anonymous_cal.jsp?resources=1294&projectId=1&calType=ical&firstDate={date-start}&lastDate={date-end}"
                    }
                  ]
                }
              ]
            },
            {
              "id": "l1meca-gcsemestre2",
              "title": "Semestre 2",
              "children": [
                {
                  "id": "meca-gc_15amth1206-sdi1202-chi1207-mtx1201-sdi1201",
                  "title": "Méca-GC_1 / 5a",
                  "url": "https://planning.univ-ubs.fr/jsp/custom/modules/plannings/anonymous_cal.jsp?resources=7218&projectId=1&calType=ical&firstDate={date-start}&lastDate={date-end}"
                },
                {
                  "id": "meca-gc_15bmth1206-sdi1202-inf1210-mtx1201-sdi1201",
                  "title": "Méca-GC_1 / 5b",
                  "url": "https://planning.univ-ubs.fr/jsp/custom/modules/plannings/anonymous_cal.jsp?resources=7219&projectId=1&calType=ical&firstDate={date-start}&lastDate={date-end}"
                },
                {
                  "id": "meca-gc_15cmth1206-sdi1202-igc1201-mtx1201-sdi1201",
                  "title": "Méca-GC_1 / 5",
                  "children": [
                    {
                      "id": "meca-gc_15c1mth1206-sdi1202-igc1201-mtx1201-sdi1201",
                      "title": "Méca-GC_1 / 5c1",
                      "url": "https://planning.univ-ubs.fr/jsp/custom/modules/plannings/anonymous_cal.jsp?resources=7225&projectId=1&calType=ical&firstDate={date-start}&lastDate={date-end}"
                    },
                    {
                      "id": "meca-gc_15c2mth1206-sdi1202-igc1201-mtx1201-sdi1201",
                      "title": "Méca-GC_1 / 5c2",
                      "url": "https://planning.univ-ubs.fr/jsp/custom/modules/plannings/anonymous_cal.jsp?resources=7227&projectId=1&calType=ical&firstDate={date-start}&lastDate={date-end}"
                    }
                  ]
                }
              ]
            }
          ]
        },
        {
          "id": "l1pei",
          "title": "L1 PEI",
          "children": [
            {
              "id": "l1pei13temps",
              "title": "L1 PEI 1/3 temps",
              "url": "https://planning.univ-ubs.fr/jsp/custom/modules/plannings/anonymous_cal.jsp?resources=9390&projectId=1&calType=ical&firstDate={date-start}&lastDate={date-end}"
            },
            {
              "id": "l1peisemestre1",
              "title": "Semestre 1",
              "children": [
                {
                  "id": "pei_171mth1106-sdi1102-inf1109-mth1107-scn1101-sdi1101",
                  "title": "Groupe TP1",
                  "url": "https://planning.univ-ubs.fr/jsp/custom/modules/plannings/anonymous_cal.jsp?resources=959&projectId=1&calType=ical&firstDate={date-start}&lastDate={date-end}"
                },
                {
                  "id": "pei_172mth1106-sdi1102-inf1109-mth1107-scn1101-sdi1101",
                  "title": "Groupe TP2",
                  "url": "https://planning.univ-ubs.fr/jsp/custom/modules/plannings/anonymous_cal.jsp?resources=4039&projectId=1&calType=ical&firstDate={date-start}&lastDate={date-end}"
                },
                {
                  "id": "pei_173mth1106-sdi1102-inf1109-mth1107-scn1101-sdi1101",
                  "title": "Groupe TP3",
                  "url": "https://planning.univ-ubs.fr/jsp/custom/modules/plannings/anonymous_cal.jsp?resources=333&projectId=1&calType=ical&firstDate={date-start}&lastDate={date-end}"
                },
                {
                  "id": "pei_174mth1106-sdi1102-inf1109-mth1107-scn1101-sdi1101",
                  "title": "Groupe TP4",
                  "url": "https://planning.univ-ubs.fr/jsp/custom/modules/plannings/anonymous_cal.jsp?resources=1578&projectId=1&calType=ical&firstDate={date-start}&lastDate={date-end}"
                }
              ]
            },
            {
              "id": "l1peisemestre2",
              "title": "Semestre 2",
              "children": [
                {
                  "id": "pei_171mth1206-scn1201-inf1210-inf1209-sdi1201-uepeis2",
                  "title": "Groupe TP1",
                  "url": "https://planning.univ-ubs.fr/jsp/custom/modules/plannings/anonymous_cal.jsp?resources=6629&projectId=1&calType=ical&firstDate={date-start}&lastDate={date-end}"
                },
                {
                  "id": "pei_172mth1206-scn1201-inf1210-inf1209-sdi1201-uepeis2",
                  "title": "Groupe TP2",
                  "url": "https://planning.univ-ubs.fr/jsp/custom/modules/plannings/anonymous_cal.jsp?resources=6619&projectId=1&calType=ical&firstDate={date-start}&lastDate={date-end}"
                },
                {
                  "id": "pei_173mth1206-scn1201-inf1210-inf1209-sdi1201-uepeis2",
                  "title": "Groupe TP3",
                  "url": "https://planning.univ-ubs.fr/jsp/custom/modules/plannings/anonymous_cal.jsp?resources=5502&projectId=1&calType=ical&firstDate={date-start}&lastDate={date-end}"
                },
                {
                  "id": "pei_174mth1206-scn1201-inf1210-inf1209-sdi1201-uepeis2",
                  "title": "Groupe TP4",
                  "url": "https://planning.univ-ubs.fr/jsp/custom/modules/plannings/anonymous_cal.jsp?resources=5340&projectId=1&calType=ical&firstDate={date-start}&lastDate={date-end}"
                }
              ]
            }
          ]
        },
        {
          "id": "l1physique",
          "title": "L1 Physique",
          "children": [
            {
              "id": "l1physique13temps",
              "title": "L1 Physique 1/3 temps",
              "url": "https://planning.univ-ubs.fr/jsp/custom/modules/plannings/anonymous_cal.jsp?resources=9389&projectId=1&calType=ical&firstDate={date-start}&lastDate={date-end}"
            },
            {
              "id": "l1physiquesemestre1",
              "title": "Semestre 1",
              "children": [
                {
                  "id": "physique_12amth1106-phy1112-chi1104-phy1113-mth1107",
                  "title": "Physique_1 / 2a",
                  "children": [
                    {
                      "id": "physique_12a1mth1106-phy1112-chi1104-phy1113-mth1107",
                      "title": "Physique_1 / 2a1",
                      "url": "https://planning.univ-ubs.fr/jsp/custom/modules/plannings/anonymous_cal.jsp?resources=7217&projectId=1&calType=ical&firstDate={date-start}&lastDate={date-end}"
                    },
                    {
                      "id": "physique_12a2mth1106-phy1112-chi1104-phy1113-mth1107",
                      "title": "Physique_1 / 2a2",
                      "url": "https://planning.univ-ubs.fr/jsp/custom/modules/plannings/anonymous_cal.jsp?resources=2352&projectId=1&calType=ical&firstDate={date-start}&lastDate={date-end}"
                    }
                  ]
                },
                {
                  "id": "physique_12bmth1106-phy1112-inf1109-phy1113-mth1107",
                  "title": "Physique_1 / 2b",
                  "children": [
                    {
                      "id": "physique_12b1mth1106-phy1112-inf1109-phy1113-mth1107",
                      "title": "Physique_1 / 2b1",
                      "url": "https://planning.univ-ubs.fr/jsp/custom/modules/plannings/anonymous_cal.jsp?resources=7220&projectId=1&calType=ical&firstDate={date-start}&lastDate={date-end}"
                    },
                    {
                      "id": "physique_12b2mth1106-phy1112-inf1109-phy1113-mth1107",
                      "title": "Physique_1 / 2b2",
                      "url": "https://planning.univ-ubs.fr/jsp/custom/modules/plannings/anonymous_cal.jsp?resources=9270&projectId=1&calType=ical&firstDate={date-start}&lastDate={date-end}"
                    }
                  ]
                }
              ]
            },
            {
              "id": "l1physiquesemestre2",
              "title": "Semestre 2",
              "children": [
                {
                  "id": "physique_12amth1206-phy1212-chi1207-mth1207-phy1213",
                  "title": "Physique_1 / 2a",
                  "children": [
                    {
                      "id": "physique_12a1mth1206-phy1212-chi1207-mth1207-phy1213",
                      "title": "Physique_1 / 2a1",
                      "url": "https://planning.univ-ubs.fr/jsp/custom/modules/plannings/anonymous_cal.jsp?resources=5065&projectId=1&calType=ical&firstDate={date-start}&lastDate={date-end}"
                    },
                    {
                      "id": "physique_12a2mth1206-phy1212-chi1207-mth1207-phy1213",
                      "title": "Physique_1 / 2a2",
                      "url": "https://planning.univ-ubs.fr/jsp/custom/modules/plannings/anonymous_cal.jsp?resources=5120&projectId=1&calType=ical&firstDate={date-start}&lastDate={date-end}"
                    }
                  ]
                },
                {
                  "id": "physique_12bmth1206-phy1212-inf1210-mth1207-phy1213",
                  "title": "Physique_1 / 2b",
                  "children": [
                    {
                      "id": "physique_12b1mth1206-phy1212-inf1210-mth1207-phy1213",
                      "title": "Physique_1 / 2b1",
                      "url": "https://planning.univ-ubs.fr/jsp/custom/modules/plannings/anonymous_cal.jsp?resources=7783&projectId=1&calType=ical&firstDate={date-start}&lastDate={date-end}"
                    },
                    {
                      "id": "physique_12b2mth1206-phy1212-inf1210-mth1207-phy1213",
                      "title": "Physique_1 / 2b2",
                      "url": "https://planning.univ-ubs.fr/jsp/custom/modules/plannings/anonymous_cal.jsp?resources=7812&projectId=1&calType=ical&firstDate={date-start}&lastDate={date-end}"
                    }
                  ]
                }
              ]
            }
          ]
        },
        {
          "id": "l1ses",
          "title": "L1 SES",
          "children": [
            {
              "id": "l1sestp1",
              "title": "L1 SES TP1",
              "url": "https://planning.univ-ubs.fr/jsp/custom/modules/plannings/anonymous_cal.jsp?resources=636&projectId=1&calType=ical&firstDate={date-start}&lastDate={date-end}"
            },
            {
              "id": "l1sestp2",
              "title": "L1 SES TP2",
              "url": "https://planning.univ-ubs.fr/jsp/custom/modules/plannings/anonymous_cal.jsp?resources=6702&projectId=1&calType=ical&firstDate={date-start}&lastDate={date-end}"
            }
          ]
        },
        {
          "id": "l1snio",
          "title": "L1 SNIO",
          "children": [
            {
              "id": "l1snio13temps",
              "title": "L1 SNIO 1/3 temps",
              "url": "https://planning.univ-ubs.fr/jsp/custom/modules/plannings/anonymous_cal.jsp?resources=9388&projectId=1&calType=ical&firstDate={date-start}&lastDate={date-end}"
            },
            {
              "id": "l1sniosemestre1",
              "title": "Semestre 1",
              "children": [
                {
                  "id": "snio_16mth1106-inf1107-inf1109-phy1113-scn1101",
                  "title": "SNIO_1 / 6",
                  "url": "https://planning.univ-ubs.fr/jsp/custom/modules/plannings/anonymous_cal.jsp?resources=7233&projectId=1&calType=ical&firstDate={date-start}&lastDate={date-end}"
                }
              ]
            },
            {
              "id": "l1sniosemestre2",
              "title": "Semestre 2",
              "children": [
                {
                  "id": "snio_161mth1206-scn1201-inf1210-inf1209-sdi1201",
                  "title": "SNIO_1 / 61",
                  "url": "https://planning.univ-ubs.fr/jsp/custom/modules/plannings/anonymous_cal.jsp?resources=8030&projectId=1&calType=ical&firstDate={date-start}&lastDate={date-end}"
                },
                {
                  "id": "snio_162mth1206-scn1201-inf1210-inf1209-sdi1201",
                  "title": "SNIO_1 / 62",
                  "url": "https://planning.univ-ubs.fr/jsp/custom/modules/plannings/anonymous_cal.jsp?resources=7235&projectId=1&calType=ical&firstDate={date-start}&lastDate={date-end}"
                }
              ]
            }
          ]
        },
        {
          "id": "l1svtletudiant",
          "title": "L1 SVT",
          "children": [
            {
              "id": "l1svtletudiantsemestre1",
              "title": "Semestre 1",
              "children": [
                {
                  "id": "bp1",
                  "title": "BP1",
                  "url": "https://planning.univ-ubs.fr/jsp/custom/modules/plannings/anonymous_cal.jsp?resources=2039&projectId=1&calType=ical&firstDate={date-start}&lastDate={date-end}"
                },
                {
                  "id": "bp2",
                  "title": "BP2",
                  "url": "https://planning.univ-ubs.fr/jsp/custom/modules/plannings/anonymous_cal.jsp?resources=990&projectId=1&calType=ical&firstDate={date-start}&lastDate={date-end}"
                },
                {
                  "id": "bp3",
                  "title": "BP3",
                  "url": "https://planning.univ-ubs.fr/jsp/custom/modules/plannings/anonymous_cal.jsp?resources=6347&projectId=1&calType=ical&firstDate={date-start}&lastDate={date-end}"
                },
                {
                  "id": "eb1",
                  "title": "EB1",
                  "url": "https://planning.univ-ubs.fr/jsp/custom/modules/plannings/anonymous_cal.jsp?resources=2029&projectId=1&calType=ical&firstDate={date-start}&lastDate={date-end}"
                },
                {
                  "id": "eb2",
                  "title": "EB2",
                  "url": "https://planning.univ-ubs.fr/jsp/custom/modules/plannings/anonymous_cal.jsp?resources=2056&projectId=1&calType=ical&firstDate={date-start}&lastDate={date-end}"
                },
                {
                  "id": "eb3",
                  "title": "EB3",
                  "url": "https://planning.univ-ubs.fr/jsp/custom/modules/plannings/anonymous_cal.jsp?resources=2070&projectId=1&calType=ical&firstDate={date-start}&lastDate={date-end}"
                },
                {
                  "id": "eb4",
                  "title": "EB4",
                  "url": "https://planning.univ-ubs.fr/jsp/custom/modules/plannings/anonymous_cal.jsp?resources=998&projectId=1&calType=ical&firstDate={date-start}&lastDate={date-end}"
                },
                {
                  "id": "eb5",
                  "title": "EB5",
                  "url": "https://planning.univ-ubs.fr/jsp/custom/modules/plannings/anonymous_cal.jsp?resources=6314&projectId=1&calType=ical&firstDate={date-start}&lastDate={date-end}"
                },
                {
                  "id": "eg1",
                  "title": "EG1",
                  "url": "https://planning.univ-ubs.fr/jsp/custom/modules/plannings/anonymous_cal.jsp?resources=2137&projectId=1&calType=ical&firstDate={date-start}&lastDate={date-end}"
                },
                {
                  "id": "eg2",
                  "title": "EG2",
                  "url": "https://planning.univ-ubs.fr/jsp/custom/modules/plannings/anonymous_cal.jsp?resources=2218&projectId=1&calType=ical&firstDate={date-start}&lastDate={date-end}"
                },
                {
                  "id": "eg3",
                  "title": "EG3",
                  "url": "https://planning.univ-ubs.fr/jsp/custom/modules/plannings/anonymous_cal.jsp?resources=787&projectId=1&calType=ical&firstDate={date-start}&lastDate={date-end}"
                },
                {
                  "id": "eg4",
                  "title": "EG4",
                  "url": "https://planning.univ-ubs.fr/jsp/custom/modules/plannings/anonymous_cal.jsp?resources=4899&projectId=1&calType=ical&firstDate={date-start}&lastDate={date-end}"
                },
                {
                  "id": "gp1",
                  "title": "GP1",
                  "url": "https://planning.univ-ubs.fr/jsp/custom/modules/plannings/anonymous_cal.jsp?resources=2010&projectId=1&calType=ical&firstDate={date-start}&lastDate={date-end}"
                },
                {
                  "id": "xxbp4-aenlever",
                  "title": "xx BP4 - a enlever",
                  "url": "https://planning.univ-ubs.fr/jsp/custom/modules/plannings/anonymous_cal.jsp?resources=4077&projectId=1&calType=ical&firstDate={date-start}&lastDate={date-end}"
                },
                {
                  "id": "xxgp2aenlever",
                  "title": "xx GP2 à enlever",
                  "url": "https://planning.univ-ubs.fr/jsp/custom/modules/plannings/anonymous_cal.jsp?resources=997&projectId=1&calType=ical&firstDate={date-start}&lastDate={date-end}"
                }
              ]
            },
            {
              "id": "l1svtletudiantsemestre2",
              "title": "Semestre 2",
              "children": [
                {
                  "id": "bg1",
                  "title": "BG1",
                  "url": "https://planning.univ-ubs.fr/jsp/custom/modules/plannings/anonymous_cal.jsp?resources=8019&projectId=1&calType=ical&firstDate={date-start}&lastDate={date-end}"
                },
                {
                  "id": "bg2",
                  "title": "BG2",
                  "url": "https://planning.univ-ubs.fr/jsp/custom/modules/plannings/anonymous_cal.jsp?resources=8020&projectId=1&calType=ical&firstDate={date-start}&lastDate={date-end}"
                },
                {
                  "id": "bp1",
                  "title": "BP1",
                  "url": "https://planning.univ-ubs.fr/jsp/custom/modules/plannings/anonymous_cal.jsp?resources=8009&projectId=1&calType=ical&firstDate={date-start}&lastDate={date-end}"
                },
                {
                  "id": "bp2",
                  "title": "BP2",
                  "url": "https://planning.univ-ubs.fr/jsp/custom/modules/plannings/anonymous_cal.jsp?resources=8010&projectId=1&calType=ical&firstDate={date-start}&lastDate={date-end}"
                },
                {
                  "id": "bp3",
                  "title": "BP3",
                  "url": "https://planning.univ-ubs.fr/jsp/custom/modules/plannings/anonymous_cal.jsp?resources=8011&projectId=1&calType=ical&firstDate={date-start}&lastDate={date-end}"
                },
                {
                  "id": "bp4",
                  "title": "BP4",
                  "url": "https://planning.univ-ubs.fr/jsp/custom/modules/plannings/anonymous_cal.jsp?resources=8012&projectId=1&calType=ical&firstDate={date-start}&lastDate={date-end}"
                },
                {
                  "id": "cg1",
                  "title": "CG1",
                  "url": "https://planning.univ-ubs.fr/jsp/custom/modules/plannings/anonymous_cal.jsp?resources=8024&projectId=1&calType=ical&firstDate={date-start}&lastDate={date-end}"
                },
                {
                  "id": "cp1",
                  "title": "CP1",
                  "url": "https://planning.univ-ubs.fr/jsp/custom/modules/plannings/anonymous_cal.jsp?resources=8022&projectId=1&calType=ical&firstDate={date-start}&lastDate={date-end}"
                },
                {
                  "id": "cp2",
                  "title": "CP2",
                  "url": "https://planning.univ-ubs.fr/jsp/custom/modules/plannings/anonymous_cal.jsp?resources=8023&projectId=1&calType=ical&firstDate={date-start}&lastDate={date-end}"
                },
                {
                  "id": "cp3",
                  "title": "CP3",
                  "url": "https://planning.univ-ubs.fr/jsp/custom/modules/plannings/anonymous_cal.jsp?resources=8014&projectId=1&calType=ical&firstDate={date-start}&lastDate={date-end}"
                },
                {
                  "id": "cp4",
                  "title": "CP4",
                  "url": "https://planning.univ-ubs.fr/jsp/custom/modules/plannings/anonymous_cal.jsp?resources=8015&projectId=1&calType=ical&firstDate={date-start}&lastDate={date-end}"
                },
                {
                  "id": "cp5",
                  "title": "CP5",
                  "url": "https://planning.univ-ubs.fr/jsp/custom/modules/plannings/anonymous_cal.jsp?resources=8016&projectId=1&calType=ical&firstDate={date-start}&lastDate={date-end}"
                },
                {
                  "id": "cp6",
                  "title": "CP6",
                  "url": "https://planning.univ-ubs.fr/jsp/custom/modules/plannings/anonymous_cal.jsp?resources=8025&projectId=1&calType=ical&firstDate={date-start}&lastDate={date-end}"
                },
                {
                  "id": "cp7",
                  "title": "CP7",
                  "url": "https://planning.univ-ubs.fr/jsp/custom/modules/plannings/anonymous_cal.jsp?resources=9444&projectId=1&calType=ical&firstDate={date-start}&lastDate={date-end}"
                },
                {
                  "id": "cp8",
                  "title": "CP8",
                  "url": "https://planning.univ-ubs.fr/jsp/custom/modules/plannings/anonymous_cal.jsp?resources=9445&projectId=1&calType=ical&firstDate={date-start}&lastDate={date-end}"
                }
              ]
            }
          ]
        }
      ]
    },
    {
      "id": "l2",
      "title": "L2",
      "children": [
        {
          "id": "l2ses",
          "title": "L2 SES",
          "children": [
            {
              "id": "l2sesgr1",
              "title": "Gr1",
              "url": "https://planning.univ-ubs.fr/jsp/custom/modules/plannings/anonymous_cal.jsp?resources=1569&projectId=1&calType=ical&firstDate={date-start}&lastDate={date-end}"
            },
            {
              "id": "l2sesgr2",
              "title": "Gr2",
              "url": "https://planning.univ-ubs.fr/jsp/custom/modules/plannings/anonymous_cal.jsp?resources=1570&projectId=1&calType=ical&firstDate={date-start}&lastDate={date-end}"
            },
            {
              "id": "l2sesgr3",
              "title": "Gr3",
              "url": "https://planning.univ-ubs.fr/jsp/custom/modules/plannings/anonymous_cal.jsp?resources=2472&projectId=1&calType=ical&firstDate={date-start}&lastDate={date-end}"
            },
            {
              "id": "l2sesme",
              "title": "ME",
              "url": "https://planning.univ-ubs.fr/jsp/custom/modules/plannings/anonymous_cal.jsp?resources=5119&projectId=1&calType=ical&firstDate={date-start}&lastDate={date-end}"
            },
            {
              "id": "l2sespc",
              "title": "PC",
              "url": "https://planning.univ-ubs.fr/jsp/custom/modules/plannings/anonymous_cal.jsp?resources=5111&projectId=1&calType=ical&firstDate={date-start}&lastDate={date-end}"
            }
          ]
        },
        {
          "id": "l2svtl",
          "title": "L2 SVT L",
          "children": [
            {
              "id": "abc1a",
              "title": "ABC1a",
              "url": "https://planning.univ-ubs.fr/jsp/custom/modules/plannings/anonymous_cal.jsp?resources=7610&projectId=1&calType=ical&firstDate={date-start}&lastDate={date-end}"
            },
            {
              "id": "abc2b",
              "title": "ABC2b",
              "url": "https://planning.univ-ubs.fr/jsp/custom/modules/plannings/anonymous_cal.jsp?resources=7611&projectId=1&calType=ical&firstDate={date-start}&lastDate={date-end}"
            },
            {
              "id": "abc3a",
              "title": "ABC3a",
              "url": "https://planning.univ-ubs.fr/jsp/custom/modules/plannings/anonymous_cal.jsp?resources=4813&projectId=1&calType=ical&firstDate={date-start}&lastDate={date-end}"
            },
            {
              "id": "abd1a",
              "title": "ABD1a",
              "url": "https://planning.univ-ubs.fr/jsp/custom/modules/plannings/anonymous_cal.jsp?resources=7612&projectId=1&calType=ical&firstDate={date-start}&lastDate={date-end}"
            },
            {
              "id": "abd2b",
              "title": "ABD2b",
              "url": "https://planning.univ-ubs.fr/jsp/custom/modules/plannings/anonymous_cal.jsp?resources=1290&projectId=1&calType=ical&firstDate={date-start}&lastDate={date-end}"
            },
            {
              "id": "abe1a",
              "title": "ABE1a",
              "url": "https://planning.univ-ubs.fr/jsp/custom/modules/plannings/anonymous_cal.jsp?resources=7613&projectId=1&calType=ical&firstDate={date-start}&lastDate={date-end}"
            },
            {
              "id": "abe2b",
              "title": "ABE2b",
              "url": "https://planning.univ-ubs.fr/jsp/custom/modules/plannings/anonymous_cal.jsp?resources=3618&projectId=1&calType=ical&firstDate={date-start}&lastDate={date-end}"
            },
            {
              "id": "acd1a",
              "title": "ACD1a",
              "url": "https://planning.univ-ubs.fr/jsp/custom/modules/plannings/anonymous_cal.jsp?resources=7618&projectId=1&calType=ical&firstDate={date-start}&lastDate={date-end}"
            },
            {
              "id": "acd2b",
              "title": "ACD2b",
              "url": "https://planning.univ-ubs.fr/jsp/custom/modules/plannings/anonymous_cal.jsp?resources=7621&projectId=1&calType=ical&firstDate={date-start}&lastDate={date-end}"
            },
            {
              "id": "ace1a",
              "title": "ACE1a",
              "url": "https://planning.univ-ubs.fr/jsp/custom/modules/plannings/anonymous_cal.jsp?resources=7623&projectId=1&calType=ical&firstDate={date-start}&lastDate={date-end}"
            },
            {
              "id": "ace2b",
              "title": "ACE2b",
              "url": "https://planning.univ-ubs.fr/jsp/custom/modules/plannings/anonymous_cal.jsp?resources=3668&projectId=1&calType=ical&firstDate={date-start}&lastDate={date-end}"
            },
            {
              "id": "bcd1a",
              "title": "BCD1a",
              "url": "https://planning.univ-ubs.fr/jsp/custom/modules/plannings/anonymous_cal.jsp?resources=7614&projectId=1&calType=ical&firstDate={date-start}&lastDate={date-end}"
            },
            {
              "id": "bcd2b",
              "title": "BCD2b",
              "url": "https://planning.univ-ubs.fr/jsp/custom/modules/plannings/anonymous_cal.jsp?resources=7615&projectId=1&calType=ical&firstDate={date-start}&lastDate={date-end}"
            },
            {
              "id": "bcd3a",
              "title": "BCD3a",
              "url": "https://planning.univ-ubs.fr/jsp/custom/modules/plannings/anonymous_cal.jsp?resources=7616&projectId=1&calType=ical&firstDate={date-start}&lastDate={date-end}"
            },
            {
              "id": "bce1a",
              "title": "BCE1a",
              "url": "https://planning.univ-ubs.fr/jsp/custom/modules/plannings/anonymous_cal.jsp?resources=4464&projectId=1&calType=ical&firstDate={date-start}&lastDate={date-end}"
            },
            {
              "id": "bce2b",
              "title": "BCE2b",
              "url": "https://planning.univ-ubs.fr/jsp/custom/modules/plannings/anonymous_cal.jsp?resources=7622&projectId=1&calType=ical&firstDate={date-start}&lastDate={date-end}"
            },
            {
              "id": "autre",
              "title": "autre",
              "url": "https://planning.univ-ubs.fr/jsp/custom/modules/plannings/anonymous_cal.jsp?resources=7617&projectId=1&calType=ical&firstDate={date-start}&lastDate={date-end}"
            },
            {
              "id": "autres",
              "title": "autres",
              "url": "https://planning.univ-ubs.fr/jsp/custom/modules/plannings/anonymous_cal.jsp?resources=7620&projectId=1&calType=ical&firstDate={date-start}&lastDate={date-end}"
            }
          ]
        },
        {
          "id": "l2pei",
          "title": "L2 PEI-A",
          "children": [
            {
              "id": "l2pei13temps",
              "title": "L2 PEI 1/3 temps",
              "url": "https://planning.univ-ubs.fr/jsp/custom/modules/plannings/anonymous_cal.jsp?resources=9384&projectId=1&calType=ical&firstDate={date-start}&lastDate={date-end}"
            },
            {
              "id": "l2peisemestre3",
              "title": "L2 PEI semestre 3",
              "children": [
                {
                  "id": "pei_271mth1309-ele1304-gif1301-sdi1304-mec1304-uepeis3",
                  "title": "Groupe TP1",
                  "url": "https://planning.univ-ubs.fr/jsp/custom/modules/plannings/anonymous_cal.jsp?resources=1745&projectId=1&calType=ical&firstDate={date-start}&lastDate={date-end}"
                },
                {
                  "id": "pei_272mth1309-ele1304-gif1301-sdi1304-mec1304-uepeis3",
                  "title": "Groupe TP2",
                  "url": "https://planning.univ-ubs.fr/jsp/custom/modules/plannings/anonymous_cal.jsp?resources=1985&projectId=1&calType=ical&firstDate={date-start}&lastDate={date-end}"
                },
                {
                  "id": "pei_273mth1309-ele1304-gif1301-sdi1304-mec1304-uepeis3",
                  "title": "Groupe TP3",
                  "url": "https://planning.univ-ubs.fr/jsp/custom/modules/plannings/anonymous_cal.jsp?resources=2045&projectId=1&calType=ical&firstDate={date-start}&lastDate={date-end}"
                }
              ]
            }
          ]
        }
      ]
    },
    {
      "id": "l3",
      "title": "L3",
      "children": [
        {
          "id": "l3biosante",
          "title": "L3 BIO SANTÉ",
          "children": [
            {
              "id": "biosantetp1",
              "title": "TP1",
              "url": "https://planning.univ-ubs.fr/jsp/custom/modules/plannings/anonymous_cal.jsp?resources=1901&projectId=1&calType=ical&firstDate={date-start}&lastDate={date-end}"
            },
            {
              "id": "biosantetp2",
              "title": "TP2",
              "url": "https://planning.univ-ubs.fr/jsp/custom/modules/plannings/anonymous_cal.jsp?resources=2223&projectId=1&calType=ical&firstDate={date-start}&lastDate={date-end}"
            }
          ]
        },
        {
          "id": "l3biotechnologies",
          "title": "L3 BIOTECHNOLOGIES",
          "children": [
            {
              "id": "biotechtp1",
              "title": "TP1",
              "url": "https://planning.univ-ubs.fr/jsp/custom/modules/plannings/anonymous_cal.jsp?resources=1920&projectId=1&calType=ical&firstDate={date-start}&lastDate={date-end}"
            },
            {
              "id": "biotechtp2",
              "title": "TP2",
              "url": "https://planning.univ-ubs.fr/jsp/custom/modules/plannings/anonymous_cal.jsp?resources=1945&projectId=1&calType=ical&firstDate={date-start}&lastDate={date-end}"
            }
          ]
        },
        {
          "id": "l3tacb",
          "title": "L3 TACB",
          "children": [
            {
              "id": "tacbtp1",
              "title": "TP1",
              "url": "https://planning.univ-ubs.fr/jsp/custom/modules/plannings/anonymous_cal.jsp?resources=1894&projectId=1&calType=ical&firstDate={date-start}&lastDate={date-end}"
            },
            {
              "id": "tacbtp2",
              "title": "TP2",
              "url": "https://planning.univ-ubs.fr/jsp/custom/modules/plannings/anonymous_cal.jsp?resources=1895&projectId=1&calType=ical&firstDate={date-start}&lastDate={date-end}"
            }
          ]
        },
        {
          "id": "l3ses",
          "title": "L3 SES",
          "children": [
            {
              "id": "l3sestp1",
              "title": "TP1",
              "url": "https://planning.univ-ubs.fr/jsp/custom/modules/plannings/anonymous_cal.jsp?resources=5417&projectId=1&calType=ical&firstDate={date-start}&lastDate={date-end}"
            },
            {
              "id": "l3sestp2",
              "title": "TP2",
              "url": "https://planning.univ-ubs.fr/jsp/custom/modules/plannings/anonymous_cal.jsp?resources=5421&projectId=1&calType=ical&firstDate={date-start}&lastDate={date-end}"
            }
          ]
        },
        {
          "id": "l3ens",
          "title": "L3 ENS",
          "children": [
            {
              "id": "l3ens-spipe",
              "title": "ENS-SPI PE",
              "url": "https://planning.univ-ubs.fr/jsp/custom/modules/plannings/anonymous_cal.jsp?resources=1669&projectId=1&calType=ical&firstDate={date-start}&lastDate={date-end}"
            },
            {
              "id": "l3ens-spisi",
              "title": "ENS-SPI SI",
              "url": "https://planning.univ-ubs.fr/jsp/custom/modules/plannings/anonymous_cal.jsp?resources=187&projectId=1&calType=ical&firstDate={date-start}&lastDate={date-end}"
            },
            {
              "id": "l3ens-svtpe",
              "title": "ENS-SVT PE",
              "url": "https://planning.univ-ubs.fr/jsp/custom/modules/plannings/anonymous_cal.jsp?resources=1708&projectId=1&calType=ical&firstDate={date-start}&lastDate={date-end}"
            },
            {
              "id": "l3ens-svtsi",
              "title": "ENS-SVT SI",
              "url": "https://planning.univ-ubs.fr/jsp/custom/modules/plannings/anonymous_cal.jsp?resources=1871&projectId=1&calType=ical&firstDate={date-start}&lastDate={date-end}"
            }
          ]
        },
        {
          "id": "l3protacb",
          "title": "L3 pro TACB",
          "children": [
            {
              "id": "tacbprotp1",
              "title": "TP1",
              "url": "https://planning.univ-ubs.fr/jsp/custom/modules/plannings/anonymous_cal.jsp?resources=1896&projectId=1&calType=ical&firstDate={date-start}&lastDate={date-end}"
            },
            {
              "id": "tacbprotp2",
              "title": "TP2",
              "url": "https://planning.univ-ubs.fr/jsp/custom/modules/plannings/anonymous_cal.jsp?resources=1282&projectId=1&calType=ical&firstDate={date-start}&lastDate={date-end}"
            }
          ]
        },
        {
          "id": "l3-pronautisme",
          "title": "L3-pro NAUTISME",
          "children": [
            {
              "id": "l3-pro-nautismegr1",
              "title": "L3-pro-NAUTISME gr 1",
              "url": "https://planning.univ-ubs.fr/jsp/custom/modules/plannings/anonymous_cal.jsp?resources=1210&projectId=1&calType=ical&firstDate={date-start}&lastDate={date-end}"
            },
            {
              "id": "l3-pro-nautismegr2",
              "title": "L3-pro-NAUTISME gr 2",
              "url": "https://planning.univ-ubs.fr/jsp/custom/modules/plannings/anonymous_cal.jsp?resources=1868&projectId=1&calType=ical&firstDate={date-start}&lastDate={date-end}"
            }
          ]
        },
        {
          "id": "l3-proemec",
          "title": "L3-pro EMEC",
          "children": [
            {
              "id": "l3-pro-emec1",
              "title": "L3-pro-EMEC 1",
              "url": "https://planning.univ-ubs.fr/jsp/custom/modules/plannings/anonymous_cal.jsp?resources=1202&projectId=1&calType=ical&firstDate={date-start}&lastDate={date-end}"
            },
            {
              "id": "l3-pro-emec2",
              "title": "L3-pro-EMEC 2",
              "url": "https://planning.univ-ubs.fr/jsp/custom/modules/plannings/anonymous_cal.jsp?resources=717&projectId=1&calType=ical&firstDate={date-start}&lastDate={date-end}"
            }
          ]
        }
      ]
    },
    {
      "id": "autre",
      "title": "Autre",
      "children": [
        {
          "id": "dui3dsante",
          "title": "DU Impression Santé",
          "children": [
            {
              "id": "dui3dsante",
              "title": "I3D Santé",
              "url": "https://planning.univ-ubs.fr/jsp/custom/modules/plannings/anonymous_cal.jsp?resources=6387&projectId=1&calType=ical&firstDate={date-start}&lastDate={date-end}"
            }
          ]
        },
        {
          "id": "i3dmci",
          "title": "DU Impression MCI",
          "children": [
            {
              "id": "i3dmci",
              "title": "I3D MCI",
              "url": "https://planning.univ-ubs.fr/jsp/custom/modules/plannings/anonymous_cal.jsp?resources=6480&projectId=1&calType=ical&firstDate={date-start}&lastDate={date-end}"
            }
          ]
        },
        {
          "id": "cpeml",
          "title": "CPEM L",
          "children": [
            {
              "id": "cpeml",
              "title": "CPEM L",
              "url": "https://planning.univ-ubs.fr/jsp/custom/modules/plannings/anonymous_cal.jsp?resources=4951&projectId=1&calType=ical&firstDate={date-start}&lastDate={date-end}"
            }
          ]
        },
        {
          "id": "duimpression3d",
          "title": "DU Impression 3D",
          "children": [
            {
              "id": "dui3dsante",
              "title": "DU I3D Santé",
              "url": "https://planning.univ-ubs.fr/jsp/custom/modules/plannings/anonymous_cal.jsp?resources=6387&projectId=1&calType=ical&firstDate={date-start}&lastDate={date-end}"
            },
            {
              "id": "i3dmci",
              "title": "I3D MCI",
              "url": "https://planning.univ-ubs.fr/jsp/custom/modules/plannings/anonymous_cal.jsp?resources=6480&projectId=1&calType=ical&firstDate={date-start}&lastDate={date-end}"
            }
          ]
        },
        {
          "id": "cpeml",
          "title": "CPEM L",
          "url": "https://planning.univ-ubs.fr/jsp/custom/modules/plannings/anonymous_cal.jsp?resources=4951&projectId=1&calType=ical&firstDate={date-start}&lastDate={date-end}"
        }
      ]
    },
    {
      "id": "m1",
      "title": "M1",
      "children": [
        {
          "id": "m1bio-bmb",
          "title": "M1 BIO - BMB",
          "children": [
            {
              "id": "s7-m1biobmb",
              "title": "S7 - M1 BIO BMB",
              "children": [
                {
                  "id": "s7grouperoscoff",
                  "title": "Groupe Roscoff",
                  "url": "https://planning.univ-ubs.fr/jsp/custom/modules/plannings/anonymous_cal.jsp?resources=5349&projectId=1&calType=ical&firstDate={date-start}&lastDate={date-end}"
                },
                {
                  "id": "s7m1bio-bmbgpa",
                  "title": "Groupe A",
                  "url": "https://planning.univ-ubs.fr/jsp/custom/modules/plannings/anonymous_cal.jsp?resources=450&projectId=1&calType=ical&firstDate={date-start}&lastDate={date-end}"
                },
                {
                  "id": "s7m1bio-bmbgpb",
                  "title": "Groupe B",
                  "url": "https://planning.univ-ubs.fr/jsp/custom/modules/plannings/anonymous_cal.jsp?resources=2880&projectId=1&calType=ical&firstDate={date-start}&lastDate={date-end}"
                }
              ]
            },
            {
              "id": "s8-m1biobmb",
              "title": "S8 - M1 BIO BMB",
              "children": [
                {
                  "id": "s8grouperoscoff",
                  "title": "Groupe Roscoff",
                  "url": "https://planning.univ-ubs.fr/jsp/custom/modules/plannings/anonymous_cal.jsp?resources=5025&projectId=1&calType=ical&firstDate={date-start}&lastDate={date-end}"
                },
                {
                  "id": "s8m1bio-bmbgpa",
                  "title": "Groupe A",
                  "url": "https://planning.univ-ubs.fr/jsp/custom/modules/plannings/anonymous_cal.jsp?resources=5030&projectId=1&calType=ical&firstDate={date-start}&lastDate={date-end}"
                },
                {
                  "id": "s8m1bio-bmbgpb",
                  "title": "Groupe B",
                  "url": "https://planning.univ-ubs.fr/jsp/custom/modules/plannings/anonymous_cal.jsp?resources=5049&projectId=1&calType=ical&firstDate={date-start}&lastDate={date-end}"
                },
                {
                  "id": "s8m1bio-bmbtp1",
                  "title": "TP1",
                  "url": "https://planning.univ-ubs.fr/jsp/custom/modules/plannings/anonymous_cal.jsp?resources=4769&projectId=1&calType=ical&firstDate={date-start}&lastDate={date-end}"
                },
                {
                  "id": "s8m1bio-bmbtp2",
                  "title": "TP2",
                  "url": "https://planning.univ-ubs.fr/jsp/custom/modules/plannings/anonymous_cal.jsp?resources=5007&projectId=1&calType=ical&firstDate={date-start}&lastDate={date-end}"
                },
                {
                  "id": "s8m1bio-3mbtp3",
                  "title": "TP3",
                  "url": "https://planning.univ-ubs.fr/jsp/custom/modules/plannings/anonymous_cal.jsp?resources=5012&projectId=1&calType=ical&firstDate={date-start}&lastDate={date-end}"
                },
                {
                  "id": "s8m1bio-bmbtp4",
                  "title": "TP4",
                  "url": "https://planning.univ-ubs.fr/jsp/custom/modules/plannings/anonymous_cal.jsp?resources=5016&projectId=1&calType=ical&firstDate={date-start}&lastDate={date-end}"
                },
                {
                  "id": "s8m1bio-bmbtp5",
                  "title": "TP5",
                  "url": "https://planning.univ-ubs.fr/jsp/custom/modules/plannings/anonymous_cal.jsp?resources=5368&projectId=1&calType=ical&firstDate={date-start}&lastDate={date-end}"
                }
              ]
            }
          ]
        },
        {
          "id": "m1-csse",
          "title": "M1-CSSE",
          "children": [
            {
              "id": "m1csse-alternants",
              "title": "Alternants",
              "url": "https://planning.univ-ubs.fr/jsp/custom/modules/plannings/anonymous_cal.jsp?resources=1893&projectId=1&calType=ical&firstDate={date-start}&lastDate={date-end}"
            },
            {
              "id": "m1csse-nonalternants",
              "title": "Non Alternants",
              "url": "https://planning.univ-ubs.fr/jsp/custom/modules/plannings/anonymous_cal.jsp?resources=7780&projectId=1&calType=ical&firstDate={date-start}&lastDate={date-end}"
            }
          ]
        },
        {
          "id": "m1-materiaux",
          "title": "M1-Matériaux",
          "children": [
            {
              "id": "m1mtx1",
              "title": "M1-Matériaux 1",
              "children": [
                {
                  "id": "m1-mtx1a",
                  "title": "Groupe A",
                  "url": "https://planning.univ-ubs.fr/jsp/custom/modules/plannings/anonymous_cal.jsp?resources=610&projectId=1&calType=ical&firstDate={date-start}&lastDate={date-end}"
                },
                {
                  "id": "m1-mtx1b",
                  "title": "Groupe B",
                  "url": "https://planning.univ-ubs.fr/jsp/custom/modules/plannings/anonymous_cal.jsp?resources=1947&projectId=1&calType=ical&firstDate={date-start}&lastDate={date-end}"
                }
              ]
            },
            {
              "id": "m1mtx2",
              "title": "M1-Matériaux 2",
              "children": [
                {
                  "id": "m1-mtx2a",
                  "title": "Groupe A",
                  "url": "https://planning.univ-ubs.fr/jsp/custom/modules/plannings/anonymous_cal.jsp?resources=1975&projectId=1&calType=ical&firstDate={date-start}&lastDate={date-end}"
                },
                {
                  "id": "m1-mtx2b",
                  "title": "Groupe B",
                  "url": "https://planning.univ-ubs.fr/jsp/custom/modules/plannings/anonymous_cal.jsp?resources=1992&projectId=1&calType=ical&firstDate={date-start}&lastDate={date-end}"
                }
              ]
            }
          ]
        },
        {
          "id": "m1-gmm",
          "title": "M1-GMM",
          "children": [
            {
              "id": "m1-gmm-tp1",
              "title": "TP1",
              "url": "https://planning.univ-ubs.fr/jsp/custom/modules/plannings/anonymous_cal.jsp?resources=683&projectId=1&calType=ical&firstDate={date-start}&lastDate={date-end}"
            },
            {
              "id": "m1-gmm-tp2",
              "title": "TP2",
              "url": "https://planning.univ-ubs.fr/jsp/custom/modules/plannings/anonymous_cal.jsp?resources=684&projectId=1&calType=ical&firstDate={date-start}&lastDate={date-end}"
            },
            {
              "id": "m1-gmm-tp3",
              "title": "TP3",
              "url": "https://planning.univ-ubs.fr/jsp/custom/modules/plannings/anonymous_cal.jsp?resources=346&projectId=1&calType=ical&firstDate={date-start}&lastDate={date-end}"
            }
          ]
        },
        {
          "id": "m1-gcamp;mp",
          "title": "M1-GC & MP",
          "children": [
            {
              "id": "m1-gcamp;mp-td1",
              "title": "TD1",
              "children": [
                {
                  "id": "m1-gcamp;mp-tp1",
                  "title": "TP1",
                  "url": "https://planning.univ-ubs.fr/jsp/custom/modules/plannings/anonymous_cal.jsp?resources=491&projectId=1&calType=ical&firstDate={date-start}&lastDate={date-end}"
                },
                {
                  "id": "m1-gcamp;mp-tp2",
                  "title": "TP2",
                  "url": "https://planning.univ-ubs.fr/jsp/custom/modules/plannings/anonymous_cal.jsp?resources=493&projectId=1&calType=ical&firstDate={date-start}&lastDate={date-end}"
                }
              ]
            },
            {
              "id": "m1-gcamp;mp-td2",
              "title": "TD2",
              "children": [
                {
                  "id": "m1-gcamp;mp-tp1",
                  "title": "TP1",
                  "url": "https://planning.univ-ubs.fr/jsp/custom/modules/plannings/anonymous_cal.jsp?resources=1252&projectId=1&calType=ical&firstDate={date-start}&lastDate={date-end}"
                },
                {
                  "id": "m1-gcamp;mp-tp2",
                  "title": "TP2",
                  "url": "https://planning.univ-ubs.fr/jsp/custom/modules/plannings/anonymous_cal.jsp?resources=1278&projectId=1&calType=ical&firstDate={date-start}&lastDate={date-end}"
                },
                {
                  "id": "m1-gcamp;mp-tp3",
                  "title": "TP3",
                  "url": "https://planning.univ-ubs.fr/jsp/custom/modules/plannings/anonymous_cal.jsp?resources=494&projectId=1&calType=ical&firstDate={date-start}&lastDate={date-end}"
                },
                {
                  "id": "m1-gcamp;mp-tp4",
                  "title": "TP4",
                  "url": "https://planning.univ-ubs.fr/jsp/custom/modules/plannings/anonymous_cal.jsp?resources=495&projectId=1&calType=ical&firstDate={date-start}&lastDate={date-end}"
                }
              ]
            }
          ]
        },
        {
          "id": "m1-ene",
          "title": "M1-ENE",
          "children": [
            {
              "id": "m1-ene1",
              "title": "Semestre 1",
              "children": [
                {
                  "id": "m1-ene1a",
                  "title": "M1 - ENE 1a",
                  "url": "https://planning.univ-ubs.fr/jsp/custom/modules/plannings/anonymous_cal.jsp?resources=2062&projectId=1&calType=ical&firstDate={date-start}&lastDate={date-end}"
                },
                {
                  "id": "m1-ene1b",
                  "title": "M1- ENE 1b",
                  "url": "https://planning.univ-ubs.fr/jsp/custom/modules/plannings/anonymous_cal.jsp?resources=2063&projectId=1&calType=ical&firstDate={date-start}&lastDate={date-end}"
                }
              ]
            },
            {
              "id": "m1-ene2",
              "title": "Semestre 2",
              "children": [
                {
                  "id": "m1-ene2a",
                  "title": "Groupe A",
                  "url": "https://planning.univ-ubs.fr/jsp/custom/modules/plannings/anonymous_cal.jsp?resources=2100&projectId=1&calType=ical&firstDate={date-start}&lastDate={date-end}"
                },
                {
                  "id": "m1-ene2b",
                  "title": "Groupe B",
                  "url": "https://planning.univ-ubs.fr/jsp/custom/modules/plannings/anonymous_cal.jsp?resources=2114&projectId=1&calType=ical&firstDate={date-start}&lastDate={date-end}"
                }
              ]
            }
          ]
        },
        {
          "id": "m1eiihispano",
          "title": "M1 EII Hispano",
          "url": "https://planning.univ-ubs.fr/jsp/custom/modules/plannings/anonymous_cal.jsp?resources=92&projectId=1&calType=ical&firstDate={date-start}&lastDate={date-end}"
        },
        {
          "id": "m1sesi",
          "title": "M1 SESI",
          "url": "https://planning.univ-ubs.fr/jsp/custom/modules/plannings/anonymous_cal.jsp?resources=1880&projectId=1&calType=ical&firstDate={date-start}&lastDate={date-end}"
        },
        {
          "id": "m1-opamp;pi",
          "title": "M1-OP&PI",
          "url": "https://planning.univ-ubs.fr/jsp/custom/modules/plannings/anonymous_cal.jsp?resources=4834&projectId=1&calType=ical&firstDate={date-start}&lastDate={date-end}"
        }
      ]
    },
    {
      "id": "m2",
      "title": "M2",
      "children": [
        {
          "id": "m2isccsse",
          "title": "M2 ISC CSSE",
          "children": [
            {
              "id": "m2isc-csse-alternants",
              "title": "Alternants",
              "url": "https://planning.univ-ubs.fr/jsp/custom/modules/plannings/anonymous_cal.jsp?resources=688&projectId=1&calType=ical&firstDate={date-start}&lastDate={date-end}"
            },
            {
              "id": "m2isc-csse-nonalternants",
              "title": "Non Alternants",
              "url": "https://planning.univ-ubs.fr/jsp/custom/modules/plannings/anonymous_cal.jsp?resources=1858&projectId=1&calType=ical&firstDate={date-start}&lastDate={date-end}"
            }
          ]
        },
        {
          "id": "m2-opamp;pi",
          "title": "M2-OP&PI",
          "children": [
            {
              "id": "m2-opamp;pi-alt",
              "title": "Alternant",
              "url": "https://planning.univ-ubs.fr/jsp/custom/modules/plannings/anonymous_cal.jsp?resources=496&projectId=1&calType=ical&firstDate={date-start}&lastDate={date-end}"
            },
            {
              "id": "m2-opamp;pi-spe",
              "title": "Spé",
              "url": "https://planning.univ-ubs.fr/jsp/custom/modules/plannings/anonymous_cal.jsp?resources=1296&projectId=1&calType=ical&firstDate={date-start}&lastDate={date-end}"
            }
          ]
        },
        {
          "id": "m2-bio-bmb",
          "title": "M2-BIO-BMB",
          "children": [
            {
              "id": "m2-bio-bmb-1",
              "title": "Groupe 1",
              "url": "https://planning.univ-ubs.fr/jsp/custom/modules/plannings/anonymous_cal.jsp?resources=320&projectId=1&calType=ical&firstDate={date-start}&lastDate={date-end}"
            },
            {
              "id": "m2-bio-bmb-2",
              "title": "Groupe 2",
              "url": "https://planning.univ-ubs.fr/jsp/custom/modules/plannings/anonymous_cal.jsp?resources=915&projectId=1&calType=ical&firstDate={date-start}&lastDate={date-end}"
            },
            {
              "id": "m2-bio-bmb-3",
              "title": "Groupe 3",
              "url": "https://planning.univ-ubs.fr/jsp/custom/modules/plannings/anonymous_cal.jsp?resources=2727&projectId=1&calType=ical&firstDate={date-start}&lastDate={date-end}"
            },
            {
              "id": "m2-bio-bmb-4",
              "title": "Groupe 4",
              "url": "https://planning.univ-ubs.fr/jsp/custom/modules/plannings/anonymous_cal.jsp?resources=2506&projectId=1&calType=ical&firstDate={date-start}&lastDate={date-end}"
            },
            {
              "id": "m2-bio-bmb-5",
              "title": "Groupe 5",
              "url": "https://planning.univ-ubs.fr/jsp/custom/modules/plannings/anonymous_cal.jsp?resources=2741&projectId=1&calType=ical&firstDate={date-start}&lastDate={date-end}"
            },
            {
              "id": "m2-bio-bmb-bam",
              "title": "BAM",
              "url": "https://planning.univ-ubs.fr/jsp/custom/modules/plannings/anonymous_cal.jsp?resources=1585&projectId=1&calType=ical&firstDate={date-start}&lastDate={date-end}"
            },
            {
              "id": "m2-bio-bmb-biomacrom",
              "title": "BIOMACROM",
              "url": "https://planning.univ-ubs.fr/jsp/custom/modules/plannings/anonymous_cal.jsp?resources=1586&projectId=1&calType=ical&firstDate={date-start}&lastDate={date-end}"
            }
          ]
        },
        {
          "id": "m2-ene",
          "title": "M2-ENE",
          "children": [
            {
              "id": "m2-ene1",
              "title": "Semestre 1",
              "children": [
                {
                  "id": "m2-ene1a_p",
                  "title": "Groupe A",
                  "url": "https://planning.univ-ubs.fr/jsp/custom/modules/plannings/anonymous_cal.jsp?resources=204&projectId=1&calType=ical&firstDate={date-start}&lastDate={date-end}"
                },
                {
                  "id": "m2-ene1b_p",
                  "title": "Groupe B",
                  "url": "https://planning.univ-ubs.fr/jsp/custom/modules/plannings/anonymous_cal.jsp?resources=205&projectId=1&calType=ical&firstDate={date-start}&lastDate={date-end}"
                }
              ]
            },
            {
              "id": "m2-ene2",
              "title": "Semestre 2",
              "children": [
                {
                  "id": "m2-ene2a_p",
                  "title": "Groupe A",
                  "url": "https://planning.univ-ubs.fr/jsp/custom/modules/plannings/anonymous_cal.jsp?resources=206&projectId=1&calType=ical&firstDate={date-start}&lastDate={date-end}"
                },
                {
                  "id": "m2-ene2b_p",
                  "title": "Groupe B",
                  "url": "https://planning.univ-ubs.fr/jsp/custom/modules/plannings/anonymous_cal.jsp?resources=207&projectId=1&calType=ical&firstDate={date-start}&lastDate={date-end}"
                }
              ]
            },
            {
              "id": "m2_ene_recherche",
              "title": "Recherche",
              "url": "https://planning.univ-ubs.fr/jsp/custom/modules/plannings/anonymous_cal.jsp?resources=1899&projectId=1&calType=ical&firstDate={date-start}&lastDate={date-end}"
            },
            {
              "id": "m2eneagstelasertinean",
              "title": "AG Stela Sertinean",
              "url": "https://planning.univ-ubs.fr/jsp/custom/modules/plannings/anonymous_cal.jsp?resources=4960&projectId=1&calType=ical&firstDate={date-start}&lastDate={date-end}"
            }
          ]
        },
        {
          "id": "m2-gc",
          "title": "M2-GC",
          "children": [
            {
              "id": "td1",
              "title": "TD1",
              "children": [
                {
                  "id": "tp1",
                  "title": "Esp. TP1",
                  "url": "https://planning.univ-ubs.fr/jsp/custom/modules/plannings/anonymous_cal.jsp?resources=4608&projectId=1&calType=ical&firstDate={date-start}&lastDate={date-end}"
                },
                {
                  "id": "tp2a",
                  "title": "TP2a",
                  "children": [
                    {
                      "id": "m2gcpalltp2a",
                      "title": "All. TP2a",
                      "url": "https://planning.univ-ubs.fr/jsp/custom/modules/plannings/anonymous_cal.jsp?resources=4786&projectId=1&calType=ical&firstDate={date-start}&lastDate={date-end}"
                    },
                    {
                      "id": "m2gcpesptp2a",
                      "title": "Esp. TP2a",
                      "url": "https://planning.univ-ubs.fr/jsp/custom/modules/plannings/anonymous_cal.jsp?resources=4868&projectId=1&calType=ical&firstDate={date-start}&lastDate={date-end}"
                    }
                  ]
                }
              ]
            },
            {
              "id": "td2",
              "title": "TD2",
              "children": [
                {
                  "id": "tp2b",
                  "title": "Esp. TP2b",
                  "url": "https://planning.univ-ubs.fr/jsp/custom/modules/plannings/anonymous_cal.jsp?resources=4861&projectId=1&calType=ical&firstDate={date-start}&lastDate={date-end}"
                },
                {
                  "id": "tp3",
                  "title": "Esp. TP3",
                  "url": "https://planning.univ-ubs.fr/jsp/custom/modules/plannings/anonymous_cal.jsp?resources=4867&projectId=1&calType=ical&firstDate={date-start}&lastDate={date-end}"
                }
              ]
            }
          ]
        },
        {
          "id": "m2-gcalt",
          "title": "M2-GC Alt.",
          "children": [
            {
              "id": "td1alt",
              "title": "TD1 Alt.",
              "children": [
                {
                  "id": "tp1alt",
                  "title": "TP1 Alt.",
                  "children": [
                    {
                      "id": "m2gcaalltp1",
                      "title": "All. TP1",
                      "url": "https://planning.univ-ubs.fr/jsp/custom/modules/plannings/anonymous_cal.jsp?resources=5854&projectId=1&calType=ical&firstDate={date-start}&lastDate={date-end}"
                    },
                    {
                      "id": "m2gcaesptp1",
                      "title": "Esp. TP1",
                      "url": "https://planning.univ-ubs.fr/jsp/custom/modules/plannings/anonymous_cal.jsp?resources=5852&projectId=1&calType=ical&firstDate={date-start}&lastDate={date-end}"
                    }
                  ]
                },
                {
                  "id": "tp2aaltesp",
                  "title": "TP2a Alt Esp",
                  "url": "https://planning.univ-ubs.fr/jsp/custom/modules/plannings/anonymous_cal.jsp?resources=8600&projectId=1&calType=ical&firstDate={date-start}&lastDate={date-end}"
                },
                {
                  "id": "tp2aaltfle",
                  "title": "TP2a Alt FLE",
                  "url": "https://planning.univ-ubs.fr/jsp/custom/modules/plannings/anonymous_cal.jsp?resources=3002&projectId=1&calType=ical&firstDate={date-start}&lastDate={date-end}"
                },
                {
                  "id": "m2gcaltpresentiel",
                  "title": "M2GC Alt Présentiel",
                  "url": "https://planning.univ-ubs.fr/jsp/custom/modules/plannings/anonymous_cal.jsp?resources=3573&projectId=1&calType=ical&firstDate={date-start}&lastDate={date-end}"
                }
              ]
            }
          ]
        },
        {
          "id": "m2-gmm",
          "title": "M2-GMM",
          "children": [
            {
              "id": "m2gm-double",
              "title": "Double",
              "url": "https://planning.univ-ubs.fr/jsp/custom/modules/plannings/anonymous_cal.jsp?resources=1870&projectId=1&calType=ical&firstDate={date-start}&lastDate={date-end}"
            },
            {
              "id": "m2gm-pur",
              "title": "Pur",
              "url": "https://planning.univ-ubs.fr/jsp/custom/modules/plannings/anonymous_cal.jsp?resources=1864&projectId=1&calType=ical&firstDate={date-start}&lastDate={date-end}"
            },
            {
              "id": "m2gmtp",
              "title": "TP",
              "url": "https://planning.univ-ubs.fr/jsp/custom/modules/plannings/anonymous_cal.jsp?resources=769&projectId=1&calType=ical&firstDate={date-start}&lastDate={date-end}"
            },
            {
              "id": "m2gmtp_1",
              "title": "TP 1",
              "url": "https://planning.univ-ubs.fr/jsp/custom/modules/plannings/anonymous_cal.jsp?resources=679&projectId=1&calType=ical&firstDate={date-start}&lastDate={date-end}"
            },
            {
              "id": "m2gmtp_2",
              "title": "TP 2",
              "url": "https://planning.univ-ubs.fr/jsp/custom/modules/plannings/anonymous_cal.jsp?resources=1564&projectId=1&calType=ical&firstDate={date-start}&lastDate={date-end}"
            },
            {
              "id": "m2gmtp_3",
              "title": "TP 3",
              "url": "https://planning.univ-ubs.fr/jsp/custom/modules/plannings/anonymous_cal.jsp?resources=899&projectId=1&calType=ical&firstDate={date-start}&lastDate={date-end}"
            }
          ]
        },
        {
          "id": "m2-ecpc",
          "title": "M2-ECPC",
          "children": [
            {
              "id": "m2-ecpc1",
              "title": "Semestre 1",
              "children": [
                {
                  "id": "m2-ecpc-1a_p",
                  "title": "Groupe A",
                  "url": "https://planning.univ-ubs.fr/jsp/custom/modules/plannings/anonymous_cal.jsp?resources=251&projectId=1&calType=ical&firstDate={date-start}&lastDate={date-end}"
                },
                {
                  "id": "m2-ecpc-1b_p",
                  "title": "Groupe B",
                  "url": "https://planning.univ-ubs.fr/jsp/custom/modules/plannings/anonymous_cal.jsp?resources=4922&projectId=1&calType=ical&firstDate={date-start}&lastDate={date-end}"
                }
              ]
            },
            {
              "id": "m2-ecpc2",
              "title": "Semestre 2",
              "children": [
                {
                  "id": "m2-ecpc-2a_p",
                  "title": "Groupe A",
                  "url": "https://planning.univ-ubs.fr/jsp/custom/modules/plannings/anonymous_cal.jsp?resources=1760&projectId=1&calType=ical&firstDate={date-start}&lastDate={date-end}"
                },
                {
                  "id": "m2-ecpc-2b_p",
                  "title": "Groupe B",
                  "url": "https://planning.univ-ubs.fr/jsp/custom/modules/plannings/anonymous_cal.jsp?resources=4924&projectId=1&calType=ical&firstDate={date-start}&lastDate={date-end}"
                }
              ]
            }
          ]
        },
        {
          "id": "m2r-mmgc",
          "title": "M2R-MMGC",
          "children": [
            {
              "id": "m2r-gc",
              "title": "M2R-GC",
              "children": [
                {
                  "id": "m2gcrall",
                  "title": "All.",
                  "url": "https://planning.univ-ubs.fr/jsp/custom/modules/plannings/anonymous_cal.jsp?resources=5215&projectId=1&calType=ical&firstDate={date-start}&lastDate={date-end}"
                },
                {
                  "id": "m2gcresp",
                  "title": "Esp.",
                  "url": "https://planning.univ-ubs.fr/jsp/custom/modules/plannings/anonymous_cal.jsp?resources=5717&projectId=1&calType=ical&firstDate={date-start}&lastDate={date-end}"
                }
              ]
            },
            {
              "id": "m2r-gm",
              "title": "M2R-GM",
              "url": "https://planning.univ-ubs.fr/jsp/custom/modules/plannings/anonymous_cal.jsp?resources=792&projectId=1&calType=ical&firstDate={date-start}&lastDate={date-end}"
            }
          ]
        },
        {
          "id": "m2-ec",
          "title": "M2-EC",
          "url": "https://planning.univ-ubs.fr/jsp/custom/modules/plannings/anonymous_cal.jsp?resources=3540&projectId=1&calType=ical&firstDate={date-start}&lastDate={date-end}"
        },
        {
          "id": "m2-eit",
          "title": "M2-EIT",
          "url": "https://planning.univ-ubs.fr/jsp/custom/modules/plannings/anonymous_cal.jsp?resources=6007&projectId=1&calType=ical&firstDate={date-start}&lastDate={date-end}"
        },
        {
          "id": "m2iscsesi",
          "title": "M2 ISC SESI",
          "url": "https://planning.univ-ubs.fr/jsp/custom/modules/plannings/anonymous_cal.jsp?resources=689&projectId=1&calType=ical&firstDate={date-start}&lastDate={date-end}"
        },
        {
          "id": "m2-i-mars",
          "title": "M2-I-Mars",
          "url": "https://planning.univ-ubs.fr/jsp/custom/modules/plannings/anonymous_cal.jsp?resources=1731&projectId=1&calType=ical&firstDate={date-start}&lastDate={date-end}"
        },
        {
          "id": "m2-c'nano",
          "title": "M2-C'Nano",
          "url": "https://planning.univ-ubs.fr/jsp/custom/modules/plannings/anonymous_cal.jsp?resources=1814&projectId=1&calType=ical&firstDate={date-start}&lastDate={date-end}"
        }
      ]
    }
  ]
}
